{
    "data": {
        "allowCheckpoints": false,
        "editorData": {
            "authorName": "Sabrina",
            "libraryVisible": false,
            "playPoint": "ghhhhhn",
            "textSize": 0
        },
        "initial": "ghhhhhn",
        "optionMirroring": true,
        "stitches": {
            "ghhhhhn": {
                "content": [
                    "Uhaaaaa! Ist das kalt. Spinnst du, kaltes Wasser auf ein altes Gebiss zu schütten?!",
                     {
                        "ifConditions": null,
                        "linkPath": null,
                        "notIfConditions": null,
                        "option": "Gegenstände sprechen nicht! [Das Gebiss ignorieren]"
                    },
					{
                        "ifConditions": null,
                        "linkPath": "wennInteressiert",
                        "notIfConditions": null,
                        "option": "Puh, die Halluzination ist hartnäckig!"
                    },
                    {
                        "ifConditions": null,
                        "linkPath": "vonWegenGutenMor",
                        "notIfConditions": null,
                        "option": "Guten Morgen!"
                    },
                   
                    {
                        "pageNum": 1
                    }
                ]
            },
            "vielZuFrhUndIchH": {
                "content": [
                    "Viel zu früh zum Reden und ich hatte noch keinen Kaffee!"
                ]
            },
            "vonWegenGutenMor": {
                "content": [
                    "Von wegen guten Morgen! Vor meinem ersten Kaffee, gibt es keinen guten Morgen!"
                ]
            },
            "wennInteressiert": {
                "content": [
                    "Die Halluzination würde gerne weiterschlafen!",
                    {
                        "ifConditions": null,
                        "linkPath": "vielZuFrhUndIchH",
                        "notIfConditions": null,
                        "option": "Hey, wenn ich Selbstgespräche führe, erwarte ich, dass man mir zuhört!"
                    }
                ]
            }
        }
    },
    "title": "Teeths",
    "url_key": 152933
}